BearSki/BearCLI.py
BearSki/CaseFactory.py
BearSki/CommandLine.py
BearSki/CommonData.py
BearSki/Manager.py
BearSki/RunUnittest.py
BearSki/__init__.py
BearSki/base.py
BearSki/core.py
BearSki/case/TestCaseSet.py
BearSki/case/TestResultSet.py
BearSki/case/TestRunnerSet.py
BearSki/case/TestSuitSet.py
BearSki/case/__init__.py
BearSki/db/Base.py
BearSki/db/__init__.py
BearSki/db/excel/__init__.py
BearSki/gui/ApiTestGui.py
BearSki/gui/__init__.py
BearSki/keywords/DataTreating.py
BearSki/keywords/RequestModelKW.py
BearSki/keywords/__init__.py
BearSki/runner/LocalReportRunner.py
BearSki/runner/ReportPage.py
BearSki/runner/__init__.py
BearSki/template/ApiTest_har.py
BearSki/template/BasicTestProject.py
BearSki/template/CreateDataTableFile.py
BearSki/template/__init__.py
BearSki/utils/DataTable.py
BearSki/utils/__init__.py
BearSki/utils/arguments.py
BearSki/utils/command.py
BearSki/utils/errors.py
BearSki/utils/hartool.py
BearSki/utils/logger.py
BearSki/utils/singleton.py
BearSki-1.5.5.dist-info/LICENSE
BearSki-1.5.5.dist-info/METADATA
BearSki-1.5.5.dist-info/WHEEL
BearSki-1.5.5.dist-info/entry_points.txt
BearSki-1.5.5.dist-info/top_level.txt
BearSki-1.5.5.dist-info/RECORD
