Metadata-Version: 2.1
Name: BearSki
Version: 1.5.5
Summary: There is a toolbox for autotest
Home-page: https://github.com/Sirius1942/BearSki
Author: chenjiusi
Author-email: UNKNOWN
License: MIT
Platform: UNKNOWN
Requires-Dist: requests
Requires-Dist: har2case
Requires-Dist: openpyxl
Requires-Dist: pyyaml
